shihiteo.py
shihiteo-1.0.0.dist-info/WHEEL
shihiteo-1.0.0.dist-info/METADATA
shihiteo-1.0.0.dist-info/RECORD
