Metadata-Version: 2.1
Name: shihiteo
Version: 1.0.0
Summary: 1000-7
Author: perfecto
Author-email: rektnpc@mail.ru
Requires-Python: >=3.7,<4.0
Classifier: Programming Language :: Python :: 3
Classifier: Programming Language :: Python :: 3.7
Classifier: Programming Language :: Python :: 3.8
Classifier: Programming Language :: Python :: 3.9
